enhancedlabelme/README.md
enhancedlabelme/__init__.py
enhancedlabelme/__main__.py
enhancedlabelme/app.py
enhancedlabelme/label_file.py
enhancedlabelme/logger.py
enhancedlabelme/shape.py
enhancedlabelme/testing.py
enhancedlabelme/cli/__init__.py
enhancedlabelme/cli/draw_json.py
enhancedlabelme/cli/draw_label_png.py
enhancedlabelme/cli/json_to_dataset.py
enhancedlabelme/cli/on_docker.py
enhancedlabelme/config/__init__.py
enhancedlabelme/config/default_config.yaml
enhancedlabelme/icons/cancel.png
enhancedlabelme/icons/close.png
enhancedlabelme/icons/color-line.png
enhancedlabelme/icons/color.png
enhancedlabelme/icons/copy.png
enhancedlabelme/icons/cross.png
enhancedlabelme/icons/cross.svg
enhancedlabelme/icons/dark.png
enhancedlabelme/icons/delete.png
enhancedlabelme/icons/done.png
enhancedlabelme/icons/done.svg
enhancedlabelme/icons/edit.png
enhancedlabelme/icons/expert.png
enhancedlabelme/icons/eye.png
enhancedlabelme/icons/feBlend-icon.png
enhancedlabelme/icons/file.png
enhancedlabelme/icons/fit-width.png
enhancedlabelme/icons/fit-window.png
enhancedlabelme/icons/fit.png
enhancedlabelme/icons/focus.png
enhancedlabelme/icons/help.png
enhancedlabelme/icons/icon.icns
enhancedlabelme/icons/icon.ico
enhancedlabelme/icons/icon.png
enhancedlabelme/icons/labels.png
enhancedlabelme/icons/labels.svg
enhancedlabelme/icons/new.png
enhancedlabelme/icons/next.png
enhancedlabelme/icons/objects.png
enhancedlabelme/icons/open.png
enhancedlabelme/icons/open.svg
enhancedlabelme/icons/prev.png
enhancedlabelme/icons/quit.png
enhancedlabelme/icons/restart.png
enhancedlabelme/icons/save-as.png
enhancedlabelme/icons/save-as.svg
enhancedlabelme/icons/save.png
enhancedlabelme/icons/save.svg
enhancedlabelme/icons/undo-cross.png
enhancedlabelme/icons/undo.png
enhancedlabelme/icons/update.png
enhancedlabelme/icons/zoom-in.png
enhancedlabelme/icons/zoom-out.png
enhancedlabelme/icons/zoom.png
enhancedlabelme/ui/penstylewindow.ui
enhancedlabelme/utils/__init__.py
enhancedlabelme/utils/_io.py
enhancedlabelme-1.8.2.dist-info/METADATA
enhancedlabelme-1.8.2.dist-info/WHEEL
enhancedlabelme-1.8.2.dist-info/entry_points.txt
enhancedlabelme-1.8.2.dist-info/top_level.txt
enhancedlabelme-1.8.2.dist-info/RECORD
