Metadata-Version: 2.1
Name: enhancedlabelme
Version: 1.8.2
Summary: Image Polygonal Annotation with Python
Home-page: https://github.com/LilactheGreat/labelme
Author: Kentaro Wada
Author-email: www.kentaro.wada@gmail.com
License: GPLv3
Keywords: Image Annotation,Machine Learning
Platform: UNKNOWN
Classifier: Development Status :: 5 - Production/Stable
Classifier: Intended Audience :: Developers
Classifier: Natural Language :: English
Classifier: Programming Language :: Python
Classifier: Programming Language :: Python :: 2.7
Classifier: Programming Language :: Python :: 3.5
Classifier: Programming Language :: Python :: 3.6
Classifier: Programming Language :: Python :: 3.7
Classifier: Programming Language :: Python :: Implementation :: CPython
Classifier: Programming Language :: Python :: Implementation :: PyPy
Requires-Dist: imgviz (>=0.11.0)
Requires-Dist: matplotlib
Requires-Dist: numpy
Requires-Dist: Pillow (>=2.8.0)
Requires-Dist: PyYAML
Requires-Dist: qtpy
Requires-Dist: termcolor
Requires-Dist: QDarkStyle (>=2.8.1)
Requires-Dist: pynput
Requires-Dist: colorama
Requires-Dist: requests
Requires-Dist: PyQt5 (>=5.12.0)
